datahelper/__init__.py
datahelper/__version__.py
datahelper/assign.py
datahelper/head.py
datahelper/pairwise.py
datahelper/pick.py
datahelper/private/__init__.py
datahelper/private/base_assign.py
datahelper/private/base_get.py
datahelper/private/base_set.py
datahelper/private/cast_path.py
datahelper/private/create.py
datahelper/private/is_numeric.py
tests/privates/__init__.py
tests/privates/test_base_assign.py
tests/privates/test_base_get.py
tests/privates/test_base_set.py
tests/privates/test_cast_path.py
tests/privates/test_create.py
tests/privates/test_is_numeric.py
datahelper-0.0.4.dist-info/LICENSE
datahelper-0.0.4.dist-info/METADATA
datahelper-0.0.4.dist-info/WHEEL
datahelper-0.0.4.dist-info/top_level.txt
datahelper-0.0.4.dist-info/RECORD
