Metadata-Version: 2.1
Name: datahelper
Version: 0.0.4
Summary: JavaScript lodash-style Python data utility library
Home-page: https://github.com/DoonDoony/datahelper
Author: DoonDoony
Author-email: cream.doondoon@gmail.com
License: MIT
Platform: any
Classifier: Development Status :: 2 - Pre-Alpha
Classifier: Intended Audience :: Developers
Classifier: Natural Language :: Korean
Classifier: License :: OSI Approved :: MIT License
Classifier: Programming Language :: Python :: 3.5
Classifier: Programming Language :: Python :: 3.6
Classifier: Programming Language :: Python :: 3.7
Classifier: Operating System :: OS Independent
Classifier: Topic :: Utilities
Requires-Python: >=3.5
